{"links": {"self": {"href": "data/repositories/osrf/gazebo_models/pullrequests/89/comments/3288320.json"}, "code": {"href": "https://api.bitbucket.org/2.0/repositories/osrf/gazebo_models/diff/osrf/gazebo_models:b33c096542d4..ea3ab0b945ea?path=drc_practice_weighted_door%2Fmeshes%2Fdoor.dae"}, "html": {"href": "#!/osrf/gazebo_models/pull-requests/89/_/diff#comment-3288320"}}, "deleted": false, "pullrequest": {"type": "pullrequest", "id": 89, "links": {"self": {"href": "data/repositories/osrf/gazebo_models/pullrequests/89.json"}, "html": {"href": "#!/osrf/gazebo_models/pull-requests/89"}}, "title": "New door for Task 5"}, "content": {"raw": "Is this door mesh the same as the mesh in the unweighted model? If so, you can reference that mesh in this model instead of including the mesh twice.", "markup": "markdown", "html": "<p>Is this door mesh the same as the mesh in the unweighted model? If so, you can reference that mesh in this model instead of including the mesh twice.</p>", "type": "rendered"}, "created_on": "2014-10-01T16:27:20.614971+00:00", "user": {"display_name": "Nate Koenig", "uuid": "{c862cdd9-fcc8-4419-9fc7-e20db14b8fcb}", "links": {"self": {"href": "https://api.bitbucket.org/2.0/users/%7Bc862cdd9-fcc8-4419-9fc7-e20db14b8fcb%7D"}, "html": {"href": "https://bitbucket.org/%7Bc862cdd9-fcc8-4419-9fc7-e20db14b8fcb%7D/"}, "avatar": {"href": "https://avatar-management--avatars.us-west-2.prod.public.atl-paas.net/557058:095b1e12-74ed-4e20-b44f-2f0745b616e0/ca24bb11-4787-4b14-a20d-d91835e9bde2/128"}}, "nickname": "Nathan Koenig", "type": "user", "account_id": "557058:095b1e12-74ed-4e20-b44f-2f0745b616e0"}, "inline": {"to": 1, "from": null, "outdated": true, "path": "drc_practice_weighted_door/meshes/door.dae"}, "updated_on": "2014-10-01T16:27:43.753495+00:00", "type": "pullrequest_comment", "id": 3288320}