{"pagelen": 50, "values": [{"update": {"description": "<?xml version=\"1.0\"?>\r\n<model>\r\n  <name>Wedge juggler</name>\r\n  <version>1.0</version>\r\n  <sdf version=\"1.5\">model.sdf</sdf>\r\n\r\n  <author>\r\n    <name>Evan Drumwright</name>\r\n    <email>drum@gwu.edu</email>\r\n  </author>\r\n\r\n  <description>\r\n    A ball-in-wedge juggler. \r\n  </description>\r\n</model>", "title": "mode11l.config", "destination": {"commit": {"hash": "8806fb2509dc", "type": "commit", "links": {"self": {"href": "data/repositories/osrf/gazebo_models/commit/8806fb2509dc.json"}, "html": {"href": "#!/osrf/gazebo_models/commits/8806fb2509dc"}}}, "repository": {"links": {"self": {"href": "data/repositories/osrf/gazebo_models.json"}, "html": {"href": "#!/osrf/gazebo_models"}, "avatar": {"href": "data/bytebucket.org/ravatar/{450079a9-f9de-40d8-9cc7-2e5115fb335b}ts=c_plus_plus"}}, "type": "repository", "name": "gazebo_models", "full_name": "osrf/gazebo_models", "uuid": "{450079a9-f9de-40d8-9cc7-2e5115fb335b}"}, "branch": {"name": "default"}}, "reason": "this looks like a duplicate of pull request #177", "source": {"commit": {"hash": "33ee7c59f24d", "type": "commit", "links": {"self": {"href": "https://api.bitbucket.org/2.0/repositories/Hunwoo/gazebo_models/commit/33ee7c59f24d"}, "html": {"href": "https://bitbucket.org/Hunwoo/gazebo_models/commits/33ee7c59f24d"}}}, "repository": {"links": {"self": {"href": "https://api.bitbucket.org/2.0/repositories/Hunwoo/gazebo_models"}, "html": {"href": "https://bitbucket.org/Hunwoo/gazebo_models"}, "avatar": {"href": "data/bytebucket.org/ravatar/{201e180d-5951-4668-832f-39d495325b7d}ts=c_plus_plus"}}, "type": "repository", "name": "gazebo_models", "full_name": "Hunwoo/gazebo_models", "uuid": "{201e180d-5951-4668-832f-39d495325b7d}"}, "branch": {"name": "aero_testing_john_louise"}}, "state": "DECLINED", "author": {"display_name": "Louise Poubel", "uuid": "{5cfa2075-477b-4ded-bdb9-8d2479544ec4}", "links": {"self": {"href": "https://api.bitbucket.org/2.0/users/%7B5cfa2075-477b-4ded-bdb9-8d2479544ec4%7D"}, "html": {"href": "https://bitbucket.org/%7B5cfa2075-477b-4ded-bdb9-8d2479544ec4%7D/"}, "avatar": {"href": "https://avatar-management--avatars.us-west-2.prod.public.atl-paas.net/557058:6ff86fcb-b7ab-44a5-b8a6-f6d9cae8b6e8/7d903d90-c5ea-4182-b7ef-0d467e9e1c74/128"}}, "nickname": "chapulina", "type": "user", "account_id": "557058:6ff86fcb-b7ab-44a5-b8a6-f6d9cae8b6e8"}, "date": "2016-07-08T01:18:53.209569+00:00"}, "pull_request": {"type": "pullrequest", "id": 208, "links": {"self": {"href": "data/repositories/osrf/gazebo_models/pullrequests/208.json"}, "html": {"href": "#!/osrf/gazebo_models/pull-requests/208"}}, "title": "mode11l.config"}}, {"update": {"description": "<?xml version=\"1.0\"?>\r\n<model>\r\n  <name>Wedge juggler</name>\r\n  <version>1.0</version>\r\n  <sdf version=\"1.5\">model.sdf</sdf>\r\n\r\n  <author>\r\n    <name>Evan Drumwright</name>\r\n    <email>drum@gwu.edu</email>\r\n  </author>\r\n\r\n  <description>\r\n    A ball-in-wedge juggler. \r\n  </description>\r\n</model>", "title": "mode11l.config", "destination": {"commit": {"hash": "8806fb2509dc", "type": "commit", "links": {"self": {"href": "data/repositories/osrf/gazebo_models/commit/8806fb2509dc.json"}, "html": {"href": "#!/osrf/gazebo_models/commits/8806fb2509dc"}}}, "repository": {"links": {"self": {"href": "data/repositories/osrf/gazebo_models.json"}, "html": {"href": "#!/osrf/gazebo_models"}, "avatar": {"href": "data/bytebucket.org/ravatar/{450079a9-f9de-40d8-9cc7-2e5115fb335b}ts=c_plus_plus"}}, "type": "repository", "name": "gazebo_models", "full_name": "osrf/gazebo_models", "uuid": "{450079a9-f9de-40d8-9cc7-2e5115fb335b}"}, "branch": {"name": "default"}}, "reason": "", "source": {"commit": {"hash": "33ee7c59f24d", "type": "commit", "links": {"self": {"href": "https://api.bitbucket.org/2.0/repositories/Hunwoo/gazebo_models/commit/33ee7c59f24d"}, "html": {"href": "https://bitbucket.org/Hunwoo/gazebo_models/commits/33ee7c59f24d"}}}, "repository": {"links": {"self": {"href": "https://api.bitbucket.org/2.0/repositories/Hunwoo/gazebo_models"}, "html": {"href": "https://bitbucket.org/Hunwoo/gazebo_models"}, "avatar": {"href": "data/bytebucket.org/ravatar/{201e180d-5951-4668-832f-39d495325b7d}ts=c_plus_plus"}}, "type": "repository", "name": "gazebo_models", "full_name": "Hunwoo/gazebo_models", "uuid": "{201e180d-5951-4668-832f-39d495325b7d}"}, "branch": {"name": "aero_testing_john_louise"}}, "state": "OPEN", "author": {"display_name": "Hunwoo Jung", "uuid": "{85203f69-c3bb-44d4-86a3-51ada0081249}", "links": {"self": {"href": "https://api.bitbucket.org/2.0/users/%7B85203f69-c3bb-44d4-86a3-51ada0081249%7D"}, "html": {"href": "https://bitbucket.org/%7B85203f69-c3bb-44d4-86a3-51ada0081249%7D/"}, "avatar": {"href": "data/secure.gravatar.com/avatar/c0ea3109791c04642d74f61fc5dd39a2d=httpsavatar-management--avatars.us-west-2.prod.public.atl-paas.netinitialsHJ-3.png"}}, "nickname": "Hunwoo", "type": "user", "account_id": "557058:7f430bb4-1471-44f1-aefb-d1acde14d8d5"}, "date": "2016-07-08T00:43:52.019358+00:00"}, "pull_request": {"type": "pullrequest", "id": 208, "links": {"self": {"href": "data/repositories/osrf/gazebo_models/pullrequests/208.json"}, "html": {"href": "#!/osrf/gazebo_models/pull-requests/208"}}, "title": "mode11l.config"}}, {"update": {"description": "<?xml version=\"1.0\"?>\r\n<model>\r\n  <name>Wedge juggler</name>\r\n  <version>1.0</version>\r\n  <sdf version=\"1.5\">model.sdf</sdf>\r\n\r\n  <author>\r\n    <name>Evan Drumwright</name>\r\n    <email>drum@gwu.edu</email>\r\n  </author>\r\n\r\n  <description>\r\n    A ball-in-wedge juggler. \r\n  </description>\r\n</model>", "title": "mode11l.config", "destination": {"commit": {"hash": "8806fb2509dc", "type": "commit", "links": {"self": {"href": "data/repositories/osrf/gazebo_models/commit/8806fb2509dc.json"}, "html": {"href": "#!/osrf/gazebo_models/commits/8806fb2509dc"}}}, "repository": {"links": {"self": {"href": "data/repositories/osrf/gazebo_models.json"}, "html": {"href": "#!/osrf/gazebo_models"}, "avatar": {"href": "data/bytebucket.org/ravatar/{450079a9-f9de-40d8-9cc7-2e5115fb335b}ts=c_plus_plus"}}, "type": "repository", "name": "gazebo_models", "full_name": "osrf/gazebo_models", "uuid": "{450079a9-f9de-40d8-9cc7-2e5115fb335b}"}, "branch": {"name": "default"}}, "reason": "", "source": {"commit": {"hash": "33ee7c59f24d", "type": "commit", "links": {"self": {"href": "https://api.bitbucket.org/2.0/repositories/Hunwoo/gazebo_models/commit/33ee7c59f24d"}, "html": {"href": "https://bitbucket.org/Hunwoo/gazebo_models/commits/33ee7c59f24d"}}}, "repository": {"links": {"self": {"href": "https://api.bitbucket.org/2.0/repositories/Hunwoo/gazebo_models"}, "html": {"href": "https://bitbucket.org/Hunwoo/gazebo_models"}, "avatar": {"href": "data/bytebucket.org/ravatar/{201e180d-5951-4668-832f-39d495325b7d}ts=c_plus_plus"}}, "type": "repository", "name": "gazebo_models", "full_name": "Hunwoo/gazebo_models", "uuid": "{201e180d-5951-4668-832f-39d495325b7d}"}, "branch": {"name": "aero_testing_john_louise"}}, "state": "OPEN", "author": {"display_name": "Hunwoo Jung", "uuid": "{85203f69-c3bb-44d4-86a3-51ada0081249}", "links": {"self": {"href": "https://api.bitbucket.org/2.0/users/%7B85203f69-c3bb-44d4-86a3-51ada0081249%7D"}, "html": {"href": "https://bitbucket.org/%7B85203f69-c3bb-44d4-86a3-51ada0081249%7D/"}, "avatar": {"href": "data/secure.gravatar.com/avatar/c0ea3109791c04642d74f61fc5dd39a2d=httpsavatar-management--avatars.us-west-2.prod.public.atl-paas.netinitialsHJ-3.png"}}, "nickname": "Hunwoo", "type": "user", "account_id": "557058:7f430bb4-1471-44f1-aefb-d1acde14d8d5"}, "date": "2016-07-08T00:43:51.986404+00:00"}, "pull_request": {"type": "pullrequest", "id": 208, "links": {"self": {"href": "data/repositories/osrf/gazebo_models/pullrequests/208.json"}, "html": {"href": "#!/osrf/gazebo_models/pull-requests/208"}}, "title": "mode11l.config"}}]}