{"links": {"self": {"href": "data/repositories/osrf/gazebo_models/pullrequests/226/comments/24354549.json"}, "code": {"href": "https://api.bitbucket.org/2.0/repositories/osrf/gazebo_models/diff/osrf/gazebo_models:da8d72ebaa51..be0498c93042?path=src_doorway%2Fmodel.sdf"}, "html": {"href": "#!/osrf/gazebo_models/pull-requests/226/_/diff#comment-24354549"}}, "deleted": false, "pullrequest": {"type": "pullrequest", "id": 226, "links": {"self": {"href": "data/repositories/osrf/gazebo_models/pullrequests/226.json"}, "html": {"href": "#!/osrf/gazebo_models/pull-requests/226"}}, "title": "Add a pushable button to the src_doorway model"}, "content": {"raw": "use [implicit_spring_damper](http://sdformat.org/spec?ver=1.6&elem=joint#ode_implicit_spring_damper) instead?", "markup": "markdown", "html": "<p>use <a data-is-external-link=\"true\" href=\"http://sdformat.org/spec?ver=1.6&amp;elem=joint#ode_implicit_spring_damper\" rel=\"nofollow\">implicit_spring_damper</a> instead?</p>", "type": "rendered"}, "created_on": "2016-09-27T17:22:55.670385+00:00", "user": {"display_name": "John Hsu", "uuid": "{0a186eae-abf0-4514-a951-23db5eccc286}", "links": {"self": {"href": "https://api.bitbucket.org/2.0/users/%7B0a186eae-abf0-4514-a951-23db5eccc286%7D"}, "html": {"href": "https://bitbucket.org/%7B0a186eae-abf0-4514-a951-23db5eccc286%7D/"}, "avatar": {"href": "https://avatar-management--avatars.us-west-2.prod.public.atl-paas.net/557058:f3968cd3-4910-4384-8349-482a6c7889ec/5445ce6e-6273-47f0-84eb-621c86ca11cb/128"}}, "nickname": "hsu", "type": "user", "account_id": "557058:f3968cd3-4910-4384-8349-482a6c7889ec"}, "inline": {"to": 436, "from": null, "outdated": true, "path": "src_doorway/model.sdf"}, "updated_on": "2016-09-27T17:22:55.672478+00:00", "type": "pullrequest_comment", "id": 24354549}